fngen/__init__.py
fngen/api_key_manager.py
fngen/cli.py
fngen/cli_util.py
fngen/decorators.py
fngen/network.py
fngen/packaging.py
fngen/resources.py
fngen/shell_util.py
fngen/commands/__init__.py
fngen/commands/infra.py
fngen/commands/login.py
fngen/commands/logs.py
fngen/commands/project.py
fngen/commands/push.py
fngen/commands/whoami.py
fngen/data/__init__.py
fngen/data/asset_manager.py
fngen/data/fixtures.py
fngen/data/hello_fastapi/app.py
fngen-0.9.20.dist-info/licenses/LICENSE
tests/__init__.py
tests/test_credentials.py
tests/test_e2e.py
fngen-0.9.20.dist-info/METADATA
fngen-0.9.20.dist-info/WHEEL
fngen-0.9.20.dist-info/entry_points.txt
fngen-0.9.20.dist-info/top_level.txt
fngen-0.9.20.dist-info/RECORD
