Metadata-Version: 2.4
Name: fngen
Version: 0.9.20
Summary: Give your Python functions superpowers
Author-email: Connor McLaughlin <connor@supadef.com>
License: MIT License
Project-URL: Homepage, https://github.com/fngen-ai/cli
Project-URL: Bug Tracker, https://github.com/fngen-ai/cli/issues
Keywords: infra,infrastructure,deployment
Classifier: Programming Language :: Python :: 3
Classifier: License :: OSI Approved :: MIT License
Classifier: Operating System :: OS Independent
Requires-Python: >=3.8
License-File: LICENSE
Requires-Dist: typer>=0.9.0
Requires-Dist: rich>=13.0.0
Requires-Dist: art>=6.4
Requires-Dist: pyyaml>=6.0
Requires-Dist: orjson<4,>=3.10
Requires-Dist: requests<3.0,>=2.25
Requires-Dist: pathspec>=0.12.1
Requires-Dist: pydantic<3.0,>=2.0
Provides-Extra: test
Requires-Dist: pytest>=8; extra == "test"
Dynamic: license-file
